{"type":"bar","data":{"labels":["world","nations","people","congress","states","united","government","national","peace","power","fear","war","autocracy","unemployed","public","policy","peaceful","income","democratic","armaments","goodwill","hope","legitimate","taxes","policies"],"datasets":[{"label":"Word Frequency","data":["22","16","15","15","14","13","12","11","11","10","10","9","8","8","7","7","6","5","4","4","4","4","4","4","4"],"backgroundColor":["rgba(73, 248,8,1.0)","rgba(158, 58,158,1.0)","rgba(213, 30,72,1.0)","rgba(199, 62,35,1.0)","rgba(161, 55,37,1.0)","rgba(182, 71,93,1.0)","rgba(190, 105,0,1.0)","rgba(118, 59,145,1.0)","rgba(0, 85,52,1.0)","rgba(129, 89,171,1.0)","rgba(148, 23,65,1.0)","rgba(179, 170,51,1.0)","rgba(244, 208,55,1.0)","rgba(3, 215,156,1.0)","rgba(223, 156,158,1.0)","rgba(182, 13,174,1.0)","rgba(98, 152,17,1.0)","rgba(213, 168,93,1.0)","rgba(189, 107,197,1.0)","rgba(54, 108,21,1.0)","rgba(222, 92,1,1.0)","rgba(117, 119,77,1.0)","rgba(104, 30,79,1.0)","rgba(95, 213,109,1.0)","rgba(221, 203,11,1.0)"],"borderColor":["rgba(73, 248,8,1)","rgba(158, 58,158,1)","rgba(213, 30,72,1)","rgba(199, 62,35,1)","rgba(161, 55,37,1)","rgba(182, 71,93,1)","rgba(190, 105,0,1)","rgba(118, 59,145,1)","rgba(0, 85,52,1)","rgba(129, 89,171,1)","rgba(148, 23,65,1)","rgba(179, 170,51,1)","rgba(244, 208,55,1)","rgba(3, 215,156,1)","rgba(223, 156,158,1)","rgba(182, 13,174,1)","rgba(98, 152,17,1)","rgba(213, 168,93,1)","rgba(189, 107,197,1)","rgba(54, 108,21,1)","rgba(222, 92,1,1)","rgba(117, 119,77,1)","rgba(104, 30,79,1)","rgba(95, 213,109,1)","rgba(221, 203,11,1)"],"borderWidth":1}]},"options":{"legend":{"display":true,"position":"right"},"responsive":false}}