{"type":"bar","data":{"labels":["security","peace","powers","recovery","unemployment","Orange"],"datasets":[{"label":"Word Frequency","data":["7","7","6","6","4",3],"backgroundColor":["rgba(130, 208,185,1.0)","rgba(19, 55,71,1.0)","rgba(121, 252,34,1.0)","rgba(211, 161,49,1.0)","rgba(165, 85,105,1.0)","rgba(255, 159, 64, 0.2)"],"borderColor":["rgba(130, 208,185,1)","rgba(19, 55,71,1)","rgba(121, 252,34,1)","rgba(211, 161,49,1)","rgba(165, 85,105,1)","rgba(255, 159, 64, 1)"],"borderWidth":1}]},"options":{"legend":{"display":true,"position":"right"},"responsive":false}}